LICENSE
MANIFEST.in
README.md
quicktest.py
settings_test.py
setup.py
django_odnoklassniki_groups.egg-info/PKG-INFO
django_odnoklassniki_groups.egg-info/SOURCES.txt
django_odnoklassniki_groups.egg-info/dependency_links.txt
django_odnoklassniki_groups.egg-info/not-zip-safe
django_odnoklassniki_groups.egg-info/requires.txt
django_odnoklassniki_groups.egg-info/top_level.txt
odnoklassniki_groups/__init__.py
odnoklassniki_groups/__init__.pyc
odnoklassniki_groups/admin.py
odnoklassniki_groups/admin.pyc
odnoklassniki_groups/factories.py
odnoklassniki_groups/factories.pyc
odnoklassniki_groups/forms.py
odnoklassniki_groups/mixins.py
odnoklassniki_groups/mixins.pyc
odnoklassniki_groups/models.py
odnoklassniki_groups/models.pyc
odnoklassniki_groups/signals.py
odnoklassniki_groups/signals.pyc
odnoklassniki_groups/tests.py
odnoklassniki_groups/tests.pyc
odnoklassniki_groups/views.py
odnoklassniki_groups/migrations/0001_initial.py
odnoklassniki_groups/migrations/0001_initial.pyc
odnoklassniki_groups/migrations/0002_auto__add_field_group_attrs.py
odnoklassniki_groups/migrations/0002_auto__add_field_group_attrs.pyc
odnoklassniki_groups/migrations/0003_auto__add_field_group_pic128x128__add_field_group_pic50x50__add_field_.py
odnoklassniki_groups/migrations/0003_auto__add_field_group_pic128x128__add_field_group_pic50x50__add_field_.pyc
odnoklassniki_groups/migrations/0004_auto__del_field_group_pic_avatar.py
odnoklassniki_groups/migrations/0004_auto__del_field_group_pic_avatar.pyc
odnoklassniki_groups/migrations/0005_auto__add_field_group_albums_count.py
odnoklassniki_groups/migrations/0005_auto__add_field_group_albums_count.pyc
odnoklassniki_groups/migrations/__init__.py
odnoklassniki_groups/migrations/__init__.pyc
odnoklassniki_groups/sql/group.postgresql_psycopg2.sql