Metadata-Version: 1.1
Name: django-odnoklassniki-groups
Version: 0.1.4
Summary: Django implementation for odnoklassniki API Groups
Home-page: https://github.com/ramusus/django-odnoklassniki-groups
Author: ramusus
Author-email: ramusus@gmail.com
License: BSD
Download-URL: http://pypi.python.org/pypi/django-odnoklassniki-groups
Platform: UNKNOWN
Classifier: Development Status :: 4 - Beta
Classifier: Environment :: Web Environment
Classifier: Intended Audience :: Developers
Classifier: License :: OSI Approved :: BSD License
Classifier: Operating System :: OS Independent
Classifier: Programming Language :: Python
Classifier: Topic :: Software Development :: Libraries :: Python Modules
